VirtualWorld/__init__.py
VirtualWorld/audio/__init__.py
VirtualWorld/video/__init__.py
test/__init__.py
VirtualWorld-2023.9.1.dist-info/LICENSE.txt
VirtualWorld-2023.9.1.dist-info/METADATA
VirtualWorld-2023.9.1.dist-info/WHEEL
VirtualWorld-2023.9.1.dist-info/top_level.txt
VirtualWorld-2023.9.1.dist-info/RECORD
